<annotation>
	<folder>Tempe</folder>
	<filename>resep-tempe-goreng-bumbu.jpeg</filename>
	<path>C:\project\IntelAI\diadiet\Dataset\Tempe\resep-tempe-goreng-bumbu.jpeg</path>
	<source>
		<database>Unknown</database>
	</source>
	<size>
		<width>750</width>
		<height>950</height>
		<depth>3</depth>
	</size>
	<segmented>0</segmented>
	<object>
		<name>Tempe</name>
		<pose>Unspecified</pose>
		<truncated>0</truncated>
		<difficult>0</difficult>
		<bndbox>
			<xmin>171</xmin>
			<ymin>535</ymin>
			<xmax>459</xmax>
			<ymax>791</ymax>
		</bndbox>
	</object>
	<object>
		<name>Tempe</name>
		<pose>Unspecified</pose>
		<truncated>0</truncated>
		<difficult>0</difficult>
		<bndbox>
			<xmin>423</xmin>
			<ymin>550</ymin>
			<xmax>594</xmax>
			<ymax>854</ymax>
		</bndbox>
	</object>
	<object>
		<name>Tempe</name>
		<pose>Unspecified</pose>
		<truncated>1</truncated>
		<difficult>0</difficult>
		<bndbox>
			<xmin>525</xmin>
			<ymin>493</ymin>
			<xmax>750</xmax>
			<ymax>745</ymax>
		</bndbox>
	</object>
</annotation>
