<annotation>
	<folder>Tahu</folder>
	<filename>Tahu Palasari Sumedang.jpg</filename>
	<path>C:\project\IntelAI\diadiet\Dataset\Tahu\Tahu Palasari Sumedang.jpg</path>
	<source>
		<database>Unknown</database>
	</source>
	<size>
		<width>550</width>
		<height>309</height>
		<depth>3</depth>
	</size>
	<segmented>0</segmented>
	<object>
		<name>Tahu</name>
		<pose>Unspecified</pose>
		<truncated>0</truncated>
		<difficult>0</difficult>
		<bndbox>
			<xmin>214</xmin>
			<ymin>134</ymin>
			<xmax>330</xmax>
			<ymax>233</ymax>
		</bndbox>
	</object>
	<object>
		<name>Tahu</name>
		<pose>Unspecified</pose>
		<truncated>0</truncated>
		<difficult>0</difficult>
		<bndbox>
			<xmin>98</xmin>
			<ymin>32</ymin>
			<xmax>224</xmax>
			<ymax>153</ymax>
		</bndbox>
	</object>
	<object>
		<name>Tahu</name>
		<pose>Unspecified</pose>
		<truncated>0</truncated>
		<difficult>0</difficult>
		<bndbox>
			<xmin>103</xmin>
			<ymin>129</ymin>
			<xmax>208</xmax>
			<ymax>284</ymax>
		</bndbox>
	</object>
	<object>
		<name>Tahu</name>
		<pose>Unspecified</pose>
		<truncated>0</truncated>
		<difficult>0</difficult>
		<bndbox>
			<xmin>337</xmin>
			<ymin>145</ymin>
			<xmax>454</xmax>
			<ymax>222</ymax>
		</bndbox>
	</object>
	<object>
		<name>Tahu</name>
		<pose>Unspecified</pose>
		<truncated>0</truncated>
		<difficult>0</difficult>
		<bndbox>
			<xmin>342</xmin>
			<ymin>38</ymin>
			<xmax>430</xmax>
			<ymax>126</ymax>
		</bndbox>
	</object>
	<object>
		<name>Tahu</name>
		<pose>Unspecified</pose>
		<truncated>0</truncated>
		<difficult>0</difficult>
		<bndbox>
			<xmin>265</xmin>
			<ymin>80</ymin>
			<xmax>340</xmax>
			<ymax>136</ymax>
		</bndbox>
	</object>
</annotation>
